{
  "settings": {
    "timezone": "Asia/Shanghai",
    "default_watch_drop_pct": -1.5,
    "default_cautious_rise_pct": 2.0,
    "intraday_drop_alert_pct": -2.5,
    "state_path": "data/state.json",
    "production": false
  },
  "funds": [
    {
      "code": "000001",
      "name": "华夏成长混合",
      "owned": true,
      "cost_nav": 1.2,
      "target_position_pct": 20,
      "watch_drop_pct": -1.5,
      "cautious_rise_pct": 2.0
    },
    {
      "code": "161725",
      "name": "招商中证白酒指数A",
      "owned": false,
      "watch_drop_pct": -2.0,
      "cautious_rise_pct": 2.0
    }
  ]
}
